{
    "pageId" : "home",
    "title" : "Home",
    "content" : "hello world",
    "backgroundImage" : 
    {
        "src" : "gradient.jpg"
    },
    "posts" : 
    [
        "flux",
        "bio",
        "bio_music",
        "bio_developer"
        
    ],

    "index" : [
        {
            "title" : "Welcome"
        },
        {
            "title" : "Bart"
        },
        {
            "title" : "van de Sande"
        },
        {
            "title" : "Developer"
        },

        {
            "title" : "Musician"
        },

        {
            "title" : "Creator"
        },

        {
            "title" : "Jazz"
        },

        {
            "title" : "Guitar"
        },

        {
            "title" : "Electronic"
        },

        {
            "title" : "Technology"
        },

        {
            "title" : "Games"
        },

        {
            "title" : "Web"
        },

        {
            "title" : "Beats"
        },

        {
            "title" : "Teaching"
        }
        ,
        {
            "title" : "Brad"
        },
        {
            "title" : "Coleman"
        }
        ,
        {
            "title" : "Nonline"
        }
    ]
}